{
  "partners": {
    "Pubmatic #2": {
      "first_seen": "2026-04-17T23:22:23.661825+00:00",
      "last_seen": "2026-04-17T23:22:23.661825+00:00",
      "last_revenue": 712.4059136199996,
      "last_impressions": 4041144
    },
    "Magnite #3": {
      "first_seen": "2026-04-17T23:22:23.661825+00:00",
      "last_seen": "2026-04-17T23:22:23.661825+00:00",
      "last_revenue": 449.2119818400002,
      "last_impressions": 706814
    },
    "Illumin Demand #29": {
      "first_seen": "2026-04-17T23:22:23.661825+00:00",
      "last_seen": "2026-04-17T23:22:23.661825+00:00",
      "last_revenue": 263.20786189999984,
      "last_impressions": 500440
    },
    "OTTA Unruly #58": {
      "first_seen": "2026-04-17T23:22:23.661825+00:00",
      "last_seen": "2026-04-17T23:22:23.661825+00:00",
      "last_revenue": 197.89479442000004,
      "last_impressions": 259003
    },
    "Unruly #4": {
      "first_seen": "2026-04-17T23:22:23.661825+00:00",
      "last_seen": "2026-04-17T23:22:23.661825+00:00",
      "last_revenue": 168.28502335000007,
      "last_impressions": 807978
    },
    "Verve #46": {
      "first_seen": "2026-04-17T23:22:23.661825+00:00",
      "last_seen": "2026-04-17T23:22:23.661825+00:00",
      "last_revenue": 133.42153635,
      "last_impressions": 543277
    },
    "OneTag #14": {
      "first_seen": "2026-04-17T23:22:23.661825+00:00",
      "last_seen": "2026-04-17T23:22:23.661825+00:00",
      "last_revenue": 58.853911399999966,
      "last_impressions": 202554
    },
    "Stirista #49": {
      "first_seen": "2026-04-17T23:22:23.661825+00:00",
      "last_seen": "2026-04-17T23:22:23.661825+00:00",
      "last_revenue": 24.029595770000004,
      "last_impressions": 14483
    },
    "AdaptMX #17": {
      "first_seen": "2026-04-17T23:22:23.661825+00:00",
      "last_seen": "2026-04-17T23:22:23.661825+00:00",
      "last_revenue": 10.302647190000004,
      "last_impressions": 15726
    },
    "Sovrn #22": {
      "first_seen": "2026-04-17T23:22:23.661825+00:00",
      "last_seen": "2026-04-17T23:22:23.661825+00:00",
      "last_revenue": 1.85616095,
      "last_impressions": 4740
    },
    "9 Dots #56": {
      "first_seen": "2026-04-17T23:22:23.661825+00:00",
      "last_seen": "2026-04-17T23:22:23.661825+00:00",
      "last_revenue": 0.9669292199999994,
      "last_impressions": 1826
    },
    "Not set #0": {
      "first_seen": "2026-04-17T23:22:23.661825+00:00",
      "last_seen": "2026-04-17T23:22:23.661825+00:00",
      "last_revenue": 0.0,
      "last_impressions": 0
    },
    "Epsilon #106": {
      "first_seen": "2026-04-17T23:22:23.661825+00:00",
      "last_seen": "2026-04-17T23:22:23.661825+00:00",
      "last_revenue": 0.0,
      "last_impressions": 0
    },
    "Spigot Spigot #87": {
      "first_seen": "2026-04-17T23:26:02.016147+00:00",
      "last_seen": "2026-04-17T23:26:02.016147+00:00",
      "last_revenue": 2.8776953700000005,
      "last_impressions": 810,
      "last_requests": 2181782
    },
    "Adapex Adapex #65": {
      "first_seen": "2026-04-17T23:26:02.016147+00:00",
      "last_seen": "2026-04-17T23:26:02.016147+00:00",
      "last_revenue": 1231.8111831200006,
      "last_impressions": 2307627,
      "last_requests": 924057971
    },
    "WeBlog WeBlog #96": {
      "first_seen": "2026-04-17T23:26:02.016147+00:00",
      "last_seen": "2026-04-17T23:26:02.016147+00:00",
      "last_revenue": 51.96970262000006,
      "last_impressions": 123714,
      "last_requests": 50838842
    },
    "Lilly  Broadcasting #141": {
      "first_seen": "2026-04-17T23:26:02.016147+00:00",
      "last_seen": "2026-04-17T23:26:02.016147+00:00",
      "last_revenue": 0.0,
      "last_impressions": 0,
      "last_requests": 8606045
    },
    "Hashtag Labs #80": {
      "first_seen": "2026-04-17T23:26:02.016147+00:00",
      "last_seen": "2026-04-17T23:26:02.016147+00:00",
      "last_revenue": 0.0,
      "last_impressions": 0,
      "last_requests": 189
    },
    "Now.gg Now.gg #59": {
      "first_seen": "2026-04-17T23:26:02.016147+00:00",
      "last_seen": "2026-04-17T23:26:02.016147+00:00",
      "last_revenue": 37.31568038999999,
      "last_impressions": 249678,
      "last_requests": 1586220015
    },
    "Ascendeum Ascendeum #48": {
      "first_seen": "2026-04-17T23:26:02.016147+00:00",
      "last_seen": "2026-04-17T23:26:02.016147+00:00",
      "last_revenue": 0.00028055,
      "last_impressions": 2,
      "last_requests": 576
    },
    "Altura Altura #19": {
      "first_seen": "2026-04-17T23:26:02.016147+00:00",
      "last_seen": "2026-04-17T23:26:02.016147+00:00",
      "last_revenue": 0.00021719000000000003,
      "last_impressions": 3,
      "last_requests": 48716
    },
    "Sovrn Sovrn #57": {
      "first_seen": "2026-04-17T23:26:02.016147+00:00",
      "last_seen": "2026-04-17T23:26:02.016147+00:00",
      "last_revenue": 0.0,
      "last_impressions": 0,
      "last_requests": 24
    },
    "PubRev PubRev #183": {
      "first_seen": "2026-04-17T23:26:02.016147+00:00",
      "last_seen": "2026-04-17T23:26:02.016147+00:00",
      "last_revenue": 0.0,
      "last_impressions": 0,
      "last_requests": 109549
    },
    "Aniview Aniview #91": {
      "first_seen": "2026-04-17T23:26:02.016147+00:00",
      "last_seen": "2026-04-17T23:26:02.016147+00:00",
      "last_revenue": 0.17201646999999995,
      "last_impressions": 166,
      "last_requests": 2876884
    },
    "TheCoolDown TheCoolDown #88": {
      "first_seen": "2026-04-17T23:26:02.016147+00:00",
      "last_seen": "2026-04-17T23:26:02.016147+00:00",
      "last_revenue": 1.38000135,
      "last_impressions": 660,
      "last_requests": 940427
    },
    "RevIQ RevIQ #32": {
      "first_seen": "2026-04-17T23:26:02.016147+00:00",
      "last_seen": "2026-04-17T23:26:02.016147+00:00",
      "last_revenue": 813.5515987400005,
      "last_impressions": 5934403,
      "last_requests": 3207857289
    },
    "Pijper Publishing #97": {
      "first_seen": "2026-04-17T23:26:02.016147+00:00",
      "last_seen": "2026-04-17T23:26:02.016147+00:00",
      "last_revenue": 59.735779849999986,
      "last_impressions": 232553,
      "last_requests": 13174624
    },
    "Vertical Scope #166": {
      "first_seen": "2026-04-17T23:26:02.016147+00:00",
      "last_seen": "2026-04-17T23:26:02.016147+00:00",
      "last_revenue": 255.30676315000005,
      "last_impressions": 361623,
      "last_requests": 186405345
    },
    "Digital1 Digital1 #56": {
      "first_seen": "2026-04-17T23:26:02.016147+00:00",
      "last_seen": "2026-04-17T23:26:02.016147+00:00",
      "last_revenue": 317.54801175999995,
      "last_impressions": 209082,
      "last_requests": 265133836
    },
    "Automattic Automattic #89": {
      "first_seen": "2026-04-17T23:26:02.016147+00:00",
      "last_seen": "2026-04-17T23:26:02.016147+00:00",
      "last_revenue": 36.506376169999974,
      "last_impressions": 186635,
      "last_requests": 124542195
    },
    "Auctus Digital #42": {
      "first_seen": "2026-04-17T23:26:02.016147+00:00",
      "last_seen": "2026-04-17T23:26:02.016147+00:00",
      "last_revenue": 7.888383070000003,
      "last_impressions": 8150,
      "last_requests": 1135252
    },
    "One Football #39": {
      "first_seen": "2026-04-17T23:26:02.016147+00:00",
      "last_seen": "2026-04-17T23:26:02.016147+00:00",
      "last_revenue": 0.0,
      "last_impressions": 0,
      "last_requests": 3551
    },
    "Factinate Factinate #167": {
      "first_seen": "2026-04-17T23:26:02.016147+00:00",
      "last_seen": "2026-04-17T23:26:02.016147+00:00",
      "last_revenue": 0.0137996,
      "last_impressions": 18,
      "last_requests": 33623
    },
    "Minute Media #21": {
      "first_seen": "2026-04-17T23:26:02.016147+00:00",
      "last_seen": "2026-04-17T23:26:02.016147+00:00",
      "last_revenue": 0.0,
      "last_impressions": 0,
      "last_requests": 3
    },
    "Landocs Landocs #66": {
      "first_seen": "2026-04-17T23:26:02.016147+00:00",
      "last_seen": "2026-04-17T23:26:02.016147+00:00",
      "last_revenue": 164.65242136000006,
      "last_impressions": 277685,
      "last_requests": 193257801
    },
    "Essentially Sports #95": {
      "first_seen": "2026-04-17T23:26:02.016147+00:00",
      "last_seen": "2026-04-17T23:26:02.016147+00:00",
      "last_revenue": 0.0,
      "last_impressions": 0,
      "last_requests": 917
    },
    "Cowles Newspaper #146": {
      "first_seen": "2026-04-17T23:26:02.016147+00:00",
      "last_seen": "2026-04-17T23:26:02.016147+00:00",
      "last_revenue": 0.7588783100000003,
      "last_impressions": 1188,
      "last_requests": 419260
    },
    "MetaSpoon MetaSpoon #114": {
      "first_seen": "2026-04-17T23:26:02.016147+00:00",
      "last_seen": "2026-04-17T23:26:02.016147+00:00",
      "last_revenue": 157.08933290999983,
      "last_impressions": 286367,
      "last_requests": 16186644
    },
    "Daily Mail #58": {
      "first_seen": "2026-04-17T23:26:02.016147+00:00",
      "last_seen": "2026-04-17T23:26:02.016147+00:00",
      "last_revenue": 0.0313984,
      "last_impressions": 20,
      "last_requests": 20707
    },
    "Ascender Ascender #40": {
      "first_seen": "2026-04-17T23:26:02.016147+00:00",
      "last_seen": "2026-04-17T23:26:02.016147+00:00",
      "last_revenue": 56.968122339999994,
      "last_impressions": 60606,
      "last_requests": 9398722
    },
    "GeeksForGeeks GeeksForGeeks #24": {
      "first_seen": "2026-04-17T23:26:02.016147+00:00",
      "last_seen": "2026-04-17T23:26:02.016147+00:00",
      "last_revenue": 691.7484475100006,
      "last_impressions": 455249,
      "last_requests": 111813210
    },
    "SportsKeeda SportsKeeda #47": {
      "first_seen": "2026-04-17T23:26:02.016147+00:00",
      "last_seen": "2026-04-17T23:26:02.016147+00:00",
      "last_revenue": 0.0,
      "last_impressions": 0,
      "last_requests": 726
    },
    "Reaction Media #103": {
      "first_seen": "2026-04-17T23:26:02.016147+00:00",
      "last_seen": "2026-04-17T23:26:02.016147+00:00",
      "last_revenue": 0.0,
      "last_impressions": 0,
      "last_requests": 9
    },
    "Ottera Ottera #115": {
      "first_seen": "2026-04-17T23:26:02.016147+00:00",
      "last_seen": "2026-04-17T23:26:02.016147+00:00",
      "last_revenue": 0.0160188,
      "last_impressions": 2,
      "last_requests": 98896
    },
    "RedFin RedFin #118": {
      "first_seen": "2026-04-17T23:26:02.016147+00:00",
      "last_seen": "2026-04-17T23:26:02.016147+00:00",
      "last_revenue": 0.0,
      "last_impressions": 0,
      "last_requests": 298
    },
    "AdVerge AdVerge #134": {
      "first_seen": "2026-04-17T23:26:02.016147+00:00",
      "last_seen": "2026-04-17T23:26:02.016147+00:00",
      "last_revenue": 89.22545902,
      "last_impressions": 413594,
      "last_requests": 188325988
    },
    "Barstool Sports #18": {
      "first_seen": "2026-04-17T23:26:02.016147+00:00",
      "last_seen": "2026-04-17T23:26:02.016147+00:00",
      "last_revenue": 6.364196650000001,
      "last_impressions": 7231,
      "last_requests": 31708962
    },
    "JPost JPost #51": {
      "first_seen": "2026-04-17T23:26:02.016147+00:00",
      "last_seen": "2026-04-17T23:26:02.016147+00:00",
      "last_revenue": 0.0,
      "last_impressions": 0,
      "last_requests": 19
    },
    "Spine Media #140": {
      "first_seen": "2026-04-17T23:26:02.016147+00:00",
      "last_seen": "2026-04-17T23:26:02.016147+00:00",
      "last_revenue": 0.0535437,
      "last_impressions": 350,
      "last_requests": 115977
    },
    "Paxa Media #104": {
      "first_seen": "2026-04-17T23:26:02.016147+00:00",
      "last_seen": "2026-04-17T23:26:02.016147+00:00",
      "last_revenue": 588.8600545600002,
      "last_impressions": 557342,
      "last_requests": 148513706
    },
    "Aditude Aditude #60": {
      "first_seen": "2026-04-17T23:26:02.016147+00:00",
      "last_seen": "2026-04-17T23:26:02.016147+00:00",
      "last_revenue": 1867.477552720008,
      "last_impressions": 9963698,
      "last_requests": 2632815628
    },
    "Paul Rumpf #93": {
      "first_seen": "2026-04-17T23:26:02.016147+00:00",
      "last_seen": "2026-04-17T23:26:02.016147+00:00",
      "last_revenue": 0.0,
      "last_impressions": 0,
      "last_requests": 272108
    },
    "Vppgamingnetwork.com Vppgamingnetwork.com #78": {
      "first_seen": "2026-04-17T23:26:02.016147+00:00",
      "last_seen": "2026-04-17T23:26:02.016147+00:00",
      "last_revenue": 4.95931008,
      "last_impressions": 43798,
      "last_requests": 3462575
    },
    "Publir Publir #9": {
      "first_seen": "2026-04-17T23:26:02.016147+00:00",
      "last_seen": "2026-04-17T23:26:02.016147+00:00",
      "last_revenue": 26.486308089999984,
      "last_impressions": 288691,
      "last_requests": 18816101
    },
    "Snackable Snackable #15": {
      "first_seen": "2026-04-17T23:26:02.016147+00:00",
      "last_seen": "2026-04-17T23:26:02.016147+00:00",
      "last_revenue": 0.03163008,
      "last_impressions": 100,
      "last_requests": 45849329
    },
    "LadBible LadBible #44": {
      "first_seen": "2026-04-17T23:26:02.016147+00:00",
      "last_seen": "2026-04-17T23:26:02.016147+00:00",
      "last_revenue": 0.0,
      "last_impressions": 0,
      "last_requests": 151945
    },
    "Blitz.GG Blitz.GG #52": {
      "first_seen": "2026-04-17T23:26:02.016147+00:00",
      "last_seen": "2026-04-17T23:26:02.016147+00:00",
      "last_revenue": 0.0,
      "last_impressions": 0,
      "last_requests": 2133
    },
    "Mission Media #112": {
      "first_seen": "2026-04-17T23:26:02.016147+00:00",
      "last_seen": "2026-04-17T23:26:02.016147+00:00",
      "last_revenue": 0.0,
      "last_impressions": 0,
      "last_requests": 19
    },
    "Zoomer Media #109": {
      "first_seen": "2026-04-17T23:26:02.016147+00:00",
      "last_seen": "2026-04-17T23:26:02.016147+00:00",
      "last_revenue": 9.810247140000001,
      "last_impressions": 31008,
      "last_requests": 8323264
    },
    "CMG CMG #12": {
      "first_seen": "2026-04-17T23:26:02.016147+00:00",
      "last_seen": "2026-04-17T23:26:02.016147+00:00",
      "last_revenue": 0.0,
      "last_impressions": 0,
      "last_requests": 3150
    },
    "Airfind Corp Airfind Corp #77": {
      "first_seen": "2026-04-17T23:26:02.016147+00:00",
      "last_seen": "2026-04-17T23:26:02.016147+00:00",
      "last_revenue": 0.0,
      "last_impressions": 0,
      "last_requests": 4855216
    },
    "Venatus Venatus #14": {
      "first_seen": "2026-04-17T23:26:02.016147+00:00",
      "last_seen": "2026-04-17T23:26:02.016147+00:00",
      "last_revenue": 0.0,
      "last_impressions": 0,
      "last_requests": 1
    },
    "Chat Blink #143": {
      "first_seen": "2026-04-17T23:26:02.016147+00:00",
      "last_seen": "2026-04-17T23:26:02.016147+00:00",
      "last_revenue": 8.199727869999998,
      "last_impressions": 26006,
      "last_requests": 40823531
    },
    "Technology Advice #177": {
      "first_seen": "2026-04-17T23:26:02.016147+00:00",
      "last_seen": "2026-04-17T23:26:02.016147+00:00",
      "last_revenue": 19.979472749999992,
      "last_impressions": 22419,
      "last_requests": 10320276
    },
    "Gamurs Gamurs #38": {
      "first_seen": "2026-04-17T23:26:02.016147+00:00",
      "last_seen": "2026-04-17T23:26:02.016147+00:00",
      "last_revenue": 0.0,
      "last_impressions": 0,
      "last_requests": 6
    },
    "Snack Media #55": {
      "first_seen": "2026-04-17T23:26:02.016147+00:00",
      "last_seen": "2026-04-17T23:26:02.016147+00:00",
      "last_revenue": 0.0,
      "last_impressions": 0,
      "last_requests": 2
    },
    "Rough Maps #36": {
      "first_seen": "2026-04-17T23:26:02.016147+00:00",
      "last_seen": "2026-04-17T23:26:02.016147+00:00",
      "last_revenue": 2605.727532439998,
      "last_impressions": 2284090,
      "last_requests": 404766292
    },
    "BidFuse Publisher #94": {
      "first_seen": "2026-04-17T23:26:02.016147+00:00",
      "last_seen": "2026-04-17T23:26:02.016147+00:00",
      "last_revenue": 2.1400000000000006,
      "last_impressions": 357,
      "last_requests": 100972360
    },
    "AnyClip AnyClip #156": {
      "first_seen": "2026-04-17T23:26:02.016147+00:00",
      "last_seen": "2026-04-17T23:26:02.016147+00:00",
      "last_revenue": 0.0011320199999999999,
      "last_impressions": 2,
      "last_requests": 167273
    }
  },
  "last_run": "2026-04-17T23:26:02.016147+00:00"
}